[{"id":123456,"name":"郑惠泽","phone":"18630372287","email":"863137401@qq.com","password":"f02f750e65ebba95ab9493cd","sex":0,"introduce":"----","time":1568640222269,"state":0,"icon":"http://127.0.0.1:1574/86.jpg"},{"id":542992,"name":"程序猿","phone":"18833896172","email":"","password":"8376ac810bb9f231d28fcf1f","sex":0,"time":1573114316003,"state":0,"introduce":"一名程序员","icon":"http://127.0.0.1:1574/86.jpg"},{"id":263278,"name":"程序猿","phone":"12345678900","email":"","password":"f02f750e65ebba95ab9493cd","sex":0,"time":1573540747845,"state":0,"introduce":"一名程序员","icon":"http://127.0.0.1:1574/86.jpg"},{"id":985716,"name":"程序猿","phone":"12345678900","email":"","password":"223bdaac071d9839536fcfdc","sex":0,"time":1573552649796,"state":0,"introduce":"一名程序员","icon":"http://127.0.0.1:1574/86.jpg"},{"id":847848,"name":"程序猿","phone":"12345678900","email":"","password":"223bdaac071d9839536fcfdc","sex":0,"time":1573552701173,"state":0,"introduce":"一名程序员","icon":"http://127.0.0.1:1574/86.jpg"},{"id":428518,"name":"程序猿","phone":"12345678900","email":"","password":"223bdaac071d9839536fcfdc","sex":0,"time":1573552738261,"state":0,"introduce":"一名程序员","icon":"http://127.0.0.1:1574/86.jpg"}]